ssl_analyzer/__init__.py
ssl_analyzer/analyzer.py
ssl_analyzer/cli.py
ssl_analyzer/utils.py
ssl_analyzer-0.1.4.dist-info/LICENSE
ssl_analyzer-0.1.4.dist-info/METADATA
ssl_analyzer-0.1.4.dist-info/WHEEL
ssl_analyzer-0.1.4.dist-info/entry_points.txt
ssl_analyzer-0.1.4.dist-info/top_level.txt
ssl_analyzer-0.1.4.dist-info/RECORD
