Metadata-Version: 2.2
Name: ssl-analyzer
Version: 0.1.4
Summary: A Python package to analyze SSL certificates
Home-page: https://github.com/TirumalaKrishnaMohanG
Author: Tirumala Krishna Mohan Gudimalla
Author-email: krishnamohan.t93@gmail.com
Classifier: Programming Language :: Python :: 3
Classifier: License :: OSI Approved :: MIT License
Classifier: Operating System :: OS Independent
Requires-Python: >=3.6
License-File: LICENSE
Requires-Dist: cryptography
Dynamic: author
Dynamic: author-email
Dynamic: classifier
Dynamic: description
Dynamic: description-content-type
Dynamic: home-page
Dynamic: requires-dist
Dynamic: requires-python
Dynamic: summary
